enpass_escape/__init__.py
enpass_escape/cli.py
enpass_escape-0.1.0.dist-info/licenses/LICENSE
enpass_escape-0.1.0.dist-info/METADATA
enpass_escape-0.1.0.dist-info/WHEEL
enpass_escape-0.1.0.dist-info/entry_points.txt
enpass_escape-0.1.0.dist-info/top_level.txt
enpass_escape-0.1.0.dist-info/RECORD
