Metadata-Version: 2.4
Name: enpass-escape
Version: 0.1.0
Summary: Since Enpass doesn't make it so easy to escape, this tool helps you to export your data in other Password Managers formats.
Author-email: ake2l <other@ke2.de>
License: MIT License
Keywords: enpass,password-manager,escape,export,import,cli
Classifier: Development Status :: 3 - Alpha
Classifier: Intended Audience :: End Users/Desktop
Classifier: License :: OSI Approved :: GNU General Public License v3 (GPLv3)
Classifier: Programming Language :: Python :: 3.11
Classifier: Programming Language :: Python :: 3.12
Classifier: Topic :: Security
Classifier: Topic :: Utilities
Requires-Python: >=3.11
License-File: LICENSE
Requires-Dist: typer[all]
Dynamic: license-file
